google/api/field_behavior_pb2.py
google/api/field_behavior_pb2.pyi
google/api/field_behavior_pb2_grpc.py
google/api/http_pb2.py
google/api/http_pb2.pyi
google/api/http_pb2_grpc.py
google/geo/type/viewport_pb2.py
google/geo/type/viewport_pb2.pyi
google/geo/type/viewport_pb2_grpc.py
google/type/calendar_period_pb2.py
google/type/calendar_period_pb2.pyi
google/type/calendar_period_pb2_grpc.py
google/type/color_pb2.py
google/type/color_pb2.pyi
google/type/color_pb2_grpc.py
google/type/date_pb2.py
google/type/date_pb2.pyi
google/type/date_pb2_grpc.py
google/type/datetime_pb2.py
google/type/datetime_pb2.pyi
google/type/datetime_pb2_grpc.py
google/type/dayofweek_pb2.py
google/type/dayofweek_pb2.pyi
google/type/dayofweek_pb2_grpc.py
google/type/decimal_pb2.py
google/type/decimal_pb2.pyi
google/type/decimal_pb2_grpc.py
google/type/expr_pb2.py
google/type/expr_pb2.pyi
google/type/expr_pb2_grpc.py
google/type/fraction_pb2.py
google/type/fraction_pb2.pyi
google/type/fraction_pb2_grpc.py
google/type/interval_pb2.py
google/type/interval_pb2.pyi
google/type/interval_pb2_grpc.py
google/type/latlng_pb2.py
google/type/latlng_pb2.pyi
google/type/latlng_pb2_grpc.py
google/type/localized_text_pb2.py
google/type/localized_text_pb2.pyi
google/type/localized_text_pb2_grpc.py
google/type/money_pb2.py
google/type/money_pb2.pyi
google/type/money_pb2_grpc.py
google/type/month_pb2.py
google/type/month_pb2.pyi
google/type/month_pb2_grpc.py
google/type/phone_number_pb2.py
google/type/phone_number_pb2.pyi
google/type/phone_number_pb2_grpc.py
google/type/postal_address_pb2.py
google/type/postal_address_pb2.pyi
google/type/postal_address_pb2_grpc.py
google/type/quaternion_pb2.py
google/type/quaternion_pb2.pyi
google/type/quaternion_pb2_grpc.py
google/type/timeofday_pb2.py
google/type/timeofday_pb2.pyi
google/type/timeofday_pb2_grpc.py
googleapis_gen-0.1.3.dist-info/LICENSE
googleapis_gen-0.1.3.dist-info/LICENSE_GOOGLE
googleapis_gen-0.1.3.dist-info/METADATA
googleapis_gen-0.1.3.dist-info/WHEEL
googleapis_gen-0.1.3.dist-info/top_level.txt
googleapis_gen-0.1.3.dist-info/RECORD
