Metadata-Version: 2.1
Name: googleapis-gen
Version: 0.1.3
Summary: Add your description here
Maintainer-email: caiyunapp <oss@caiyunapp.com>, ringsaturn <ringsaturn.me@gmail.com>
License: Apache License
Requires-Python: >=3.12
License-File: LICENSE
License-File: LICENSE_GOOGLE
Requires-Dist: protobuf >=5.28.3
